README.md
setup.py
aidedp/__init__.py
aidedp/test.py
aidedp.egg-info/PKG-INFO
aidedp.egg-info/SOURCES.txt
aidedp.egg-info/dependency_links.txt
aidedp.egg-info/requires.txt
aidedp.egg-info/top_level.txt