Metadata-Version: 2.1
Name: aidedp
Version: 0.0.1
Summary: Someones leetspeak that supports Windows, MacOS, and Linux
Author: xiaobai
Author-email: 
Keywords: python,mac,windows
Classifier: Development Status :: 1 - Planning
Classifier: Intended Audience :: Developers
Classifier: Programming Language :: Python :: 3
Classifier: Operating System :: Unix
Classifier: Operating System :: MacOS :: MacOS X
Classifier: Operating System :: Microsoft :: Windows
Requires-Dist: getch; platform_system == "Unix"
Requires-Dist: getch; platform_system == "MacOS"
